LICENSE
MANIFEST.in
README.md
setup.cfg
setup.py
pinkopy/__init__.py
pinkopy/base_session.py
pinkopy/clients.py
pinkopy/commvault.py
pinkopy/exceptions.py
pinkopy/jobs.py
pinkopy/subclients.py
pinkopy.egg-info/PKG-INFO
pinkopy.egg-info/SOURCES.txt
pinkopy.egg-info/dependency_links.txt
pinkopy.egg-info/requires.txt
pinkopy.egg-info/top_level.txt
tests/__init__.py
tests/pinkopy/__init__.py
tests/pinkopy/test_base_session.py
tests/pinkopy/test_commvault.py
tests/pinkopy/test_exceptions.py
tests/pinkopy/test_helper.py