Metadata-Version: 1.1
Name: pinkopy
Version: 2.1.2
Summary: Python wrapper for Commvault api
Home-page: https://github.com/theherk/pinkopy
Author: Herkermer Sherwood
Author-email: theherk@gmail.com
License: MIT
Download-URL: https://github.com/theherk/pinkopy/archive/2.1.2.zip
Platform: all
Classifier: Development Status :: 4 - Beta
Classifier: License :: Other/Proprietary License
Classifier: License :: OSI Approved :: MIT License
Classifier: Environment :: Console
Classifier: Intended Audience :: Developers
Classifier: Intended Audience :: System Administrators
Classifier: Operating System :: MacOS :: MacOS X
Classifier: Operating System :: Unix
Classifier: Operating System :: POSIX
Classifier: Programming Language :: Python :: 3.2
Classifier: Programming Language :: Python :: 3.3
Classifier: Programming Language :: Python :: 3.4
Classifier: Programming Language :: Python :: 3.5
Classifier: Topic :: Utilities
